MANIFEST.in
README.rst
setup.cfg
setup.py
savu/__init__.py
savu/tomo_recon.py
savu/tomo_recon_mpi.py
savu.egg-info/PKG-INFO
savu.egg-info/SOURCES.txt
savu.egg-info/dependency_links.txt
savu.egg-info/not-zip-safe
savu.egg-info/top_level.txt
savu/core/__init__.py
savu/core/process.py
savu/data/__init__.py
savu/data/process_data.py
savu/data/structures.py
savu/mpi_test/__init__.py
savu/mpi_test/dls/__init__.py
savu/mpi_test/dls/framework_file_test_runner.py
savu/mpi_test/dls/framework_test_runner.py
savu/mpi_test/dls/plugin_test_runner.py
savu/plugins/__init__.py
savu/plugins/astra_recon.py
savu/plugins/base_recon.py
savu/plugins/cpu_plugin.py
savu/plugins/filter.py
savu/plugins/gpu_plugin.py
savu/plugins/manchester_recon.py
savu/plugins/median_filter.py
savu/plugins/pass_through_plugin.py
savu/plugins/plugin.py
savu/plugins/simple_fake_gpu_recon.py
savu/plugins/simple_recon.py
savu/plugins/timeseries_field_corrections.py
savu/plugins/utils.py
savu/plugins/vo_centering.py
savu/test/__init__.py
savu/test/framework_test.py
savu/test/plugin_test.py
savu/test/plugins_util_test.py
savu/test/process_file_test.py
savu/test/process_file_test_2.py
savu/test/structures_test.py
savu/test/test_util_test.py
savu/test/test_utils.py