Metadata-Version: 1.1
Name: savu
Version: 0.1
Summary: Savu Python Tomography Pipeline
Home-page: UNKNOWN
Author: Mark Basham
Author-email: scientificsoftware@diamond.ac.uk
License: Apache License, Version 2.0
Platform: UNKNOWN
Classifier: Development Status :: 1 - Planning
Classifier: Intended Audience :: Science/Research
Classifier: License :: OSI Approved :: Apache Software License
Classifier: Natural Language :: English
Classifier: Programming Language :: Python :: 2.7
Classifier: Topic :: Scientific/Engineering
